autolgb/__init__.py
autolgb/autolgb.py
autolgb/logger.py
autolgb/params.py
autolgb/schemas.py
autolgb/utils.py
kaggle_autolgb-0.0.6.dist-info/LICENCE
kaggle_autolgb-0.0.6.dist-info/METADATA
kaggle_autolgb-0.0.6.dist-info/WHEEL
kaggle_autolgb-0.0.6.dist-info/top_level.txt
kaggle_autolgb-0.0.6.dist-info/RECORD
