Metadata-Version: 2.1
Name: kaggle-autolgb
Version: 0.0.6
Summary: tune with optuna and model LightGBM
Home-page: https://github.com/Aditta-das/kaggle-autolgb.git
Author: Aditta Das Nishad
Author-email: nishad009adi@gmail.com
License: UNKNOWN
Platform: linux
Platform: unix
Requires-Python: >=3.6
Requires-Dist: joblib
Requires-Dist: lightgbm
Requires-Dist: logger
Requires-Dist: numpy
Requires-Dist: optuna
Requires-Dist: pandas
Requires-Dist: pyarrow
Requires-Dist: pydantic
Requires-Dist: scikit-learn
